deepthought/__init__.py
deepthought/core/DTModel.py
deepthought/core/DTParams.py
deepthought/core/DTResponse.py
deepthought/core/__init__.py
deepthought/store/DTPreparedQueryBuilder.py
deepthought/store/DTQueryBuilder.py
deepthought/store/DTStore.py
deepthought/store/__init__.py
deepthought/store/mysql/DTMySQLDatabase.py
deepthought/store/mysql/__init__.py
deepthought/store/pgsql/DTPgSQLDatabase.py
deepthought/store/pgsql/__init__.py
deepthought/store/sqlite/DTSQLiteDatabase.py
deepthought/store/sqlite/__init__.py
deepthought/tests/DTTestCase.py
deepthought/tests/__init__.py
deepthought/utils/DTLog.py
deepthought/utils/DTSettings.py
deepthought/utils/DTSettingsConfig.py
deepthought/utils/DTSettingsStorage.py
deepthought/utils/__init__.py
deepthought-1.0.13.dist-info/DESCRIPTION.rst
deepthought-1.0.13.dist-info/METADATA
deepthought-1.0.13.dist-info/RECORD
deepthought-1.0.13.dist-info/WHEEL
deepthought-1.0.13.dist-info/metadata.json
deepthought-1.0.13.dist-info/top_level.txt
